tequila-1.1.1.data/scripts/tequila
tequila-1.1.1.dist-info/top_level.txt
tequila-1.1.1.dist-info/RECORD
tequila-1.1.1.dist-info/metadata.json
tequila-1.1.1.dist-info/WHEEL
tequila-1.1.1.dist-info/DESCRIPTION.rst
tequila-1.1.1.dist-info/METADATA
tequila/__init__.py
tequila/net.py
tequila/command.py
tequila/exception.py
tequila/daemonize.py
tequila/config.py
tequila/util.py
tequila/resources/server_base/start
tequila/resources/server_base/serverctl
tequila/resources/server_base/config/tequila.config
tequila/resources/server_base/config/jvm.opts
tequila/resources/server_base/config/log4j2.xml
tequila/resources/server_base/config/application.opts
tequila/network/__init__.py
tequila/network/download.py
tequila/network/maven.py
tequila/version/__init__.py
tequila/version/backup.py
tequila/version/git.py
tequila/server/__init__.py
tequila/server/control.py
tequila/server/filesystem.py
tequila/server/instance.py
tequila/server/exception.py
tequila/server/config.py
tequila/server/wrapper/__init__.py
tequila/server/wrapper/screen.py
tequila/server/wrapper/daemon.py
tequila/server/group/__init__.py
tequila/server/group/exception.py
tequila/server/group/config.py
etc/tequila/tequila.conf
