Metadata-Version: 2.0
Name: tequila
Version: 1.1.1
Summary: A minecraft server manager
Home-page: http://github.com/Snaipe/tequila
Author: Snaipe
Author-email: franklinmathieu@gmail.com
License: GPLv3
Keywords: minecraft server manager
Platform: UNKNOWN
Classifier: Development Status :: 5 - Production/Stable
Classifier: Environment :: Console
Classifier: License :: OSI Approved :: GNU General Public License v3 or later (GPLv3+)
Classifier: Operating System :: POSIX
Classifier: Programming Language :: Python :: 3.4
Classifier: Topic :: System :: Systems Administration
Classifier: Topic :: Utilities
Requires: baker
